<?xml version="1.0" encoding="UTF-8"?>
<modsCollection xmlns="http://www.loc.gov/mods/v3">
<mods ID="somashekarappa-etal-2022-mutual">
    <titleInfo>
        <title>Mutual gaze detection and estimation: towards human-robot interaction</title>
    </titleInfo>
    <name type="personal">
        <namePart type="given">Vidya</namePart>
        <namePart type="family">Somashekarappa</namePart>
        <role>
            <roleTerm authority="marcrelator" type="text">author</roleTerm>
        </role>
    </name>
    <name type="personal">
        <namePart type="given">Christine</namePart>
        <namePart type="family">Howes</namePart>
        <role>
            <roleTerm authority="marcrelator" type="text">author</roleTerm>
        </role>
    </name>
    <name type="personal">
        <namePart type="given">Asad</namePart>
        <namePart type="family">Sayeed</namePart>
        <role>
            <roleTerm authority="marcrelator" type="text">author</roleTerm>
        </role>
    </name>
    <originInfo>
        <dateIssued>2022-08</dateIssued>
    </originInfo>
    <typeOfResource>text</typeOfResource>
    <relatedItem type="host">
        <titleInfo>
            <title>Proceedings of the 26th Workshop on the Semantics and Pragmatics of Dialogue - Poster Abstracts</title>
        </titleInfo>
        <originInfo>
            <publisher>SEMDIAL</publisher>
            <place>
                <placeTerm type="text">Dublin, Ireland</placeTerm>
            </place>
        </originInfo>
        <genre authority="marcgt">conference publication</genre>
    </relatedItem>
    <identifier type="citekey">somashekarappa-etal-2022-mutual</identifier>
    <location>
        <url>http://semdial.org/anthology/Z22-Somashekarappa_semdial_0041.pdf</url>
    </location>
    <part>
        <date>2022-08</date>
    </part>
</mods>
</modsCollection>
