<?xml version="1.0" encoding="UTF-8"?>
<modsCollection xmlns="http://www.loc.gov/mods/v3">
<mods ID="tenbrink-etal-2008-negotiating">
    <titleInfo>
        <title>Negotiating Spatial Relationships in Dialogue: The role of the addressee</title>
    </titleInfo>
    <name type="personal">
        <namePart type="given">Thora</namePart>
        <namePart type="family">Tenbrink</namePart>
        <role>
            <roleTerm authority="marcrelator" type="text">author</roleTerm>
        </role>
    </name>
    <name type="personal">
        <namePart type="given">Elena</namePart>
        <namePart type="family">Andonova</namePart>
        <role>
            <roleTerm authority="marcrelator" type="text">author</roleTerm>
        </role>
    </name>
    <name type="personal">
        <namePart type="given">Kenny</namePart>
        <namePart type="family">Coventry</namePart>
        <role>
            <roleTerm authority="marcrelator" type="text">author</roleTerm>
        </role>
    </name>
    <originInfo>
        <dateIssued>2008-06</dateIssued>
    </originInfo>
    <typeOfResource>text</typeOfResource>
    <relatedItem type="host">
        <titleInfo>
            <title>Proceedings of the 12th Workshop on the Semantics and Pragmatics of Dialogue - Poster Abstracts</title>
        </titleInfo>
        <originInfo>
            <publisher>SEMDIAL</publisher>
            <place>
                <placeTerm type="text">London, United Kingdom</placeTerm>
            </place>
        </originInfo>
        <genre authority="marcgt">conference publication</genre>
    </relatedItem>
    <identifier type="citekey">tenbrink-etal-2008-negotiating</identifier>
    <location>
        <url>http://semdial.org/anthology/Z08-Tenbrink_semdial_0034.pdf</url>
    </location>
    <part>
        <date>2008-06</date>
    </part>
</mods>
</modsCollection>
