<?xml version="1.0" encoding="UTF-8"?>
<modsCollection xmlns="http://www.loc.gov/mods/v3">
<mods ID="michel-lehuen-2005-robust">
    <titleInfo>
        <title>Robust Semantic Interpretation and Dialog Management in the Contect of a CALL Application</title>
    </titleInfo>
    <name type="personal">
        <namePart type="given">Johan</namePart>
        <namePart type="family">Michel</namePart>
        <role>
            <roleTerm authority="marcrelator" type="text">author</roleTerm>
        </role>
    </name>
    <name type="personal">
        <namePart type="given">Jérôme</namePart>
        <namePart type="family">Lehuen</namePart>
        <role>
            <roleTerm authority="marcrelator" type="text">author</roleTerm>
        </role>
    </name>
    <originInfo>
        <dateIssued>2005-jun 9-11</dateIssued>
    </originInfo>
    <typeOfResource>text</typeOfResource>
    <relatedItem type="host">
        <titleInfo>
            <title>Proceedings of the 9th Workshop on the Semantics and Pragmatics of Dialogue - Poster Abstracts</title>
        </titleInfo>
        <originInfo>
            <publisher>SEMDIAL</publisher>
            <place>
                <placeTerm type="text">Nancy, France</placeTerm>
            </place>
        </originInfo>
        <genre authority="marcgt">conference publication</genre>
    </relatedItem>
    <identifier type="citekey">michel-lehuen-2005-robust</identifier>
    <location>
        <url>http://semdial.org/anthology/019_Michel_semdial2005_dialor_proceedings.pdf</url>
    </location>
    <part>
        <date>2005-jun 9-11</date>
    </part>
</mods>
</modsCollection>
